claspin-0.0.1.dist-info/METADATA
claspin-0.0.1.dist-info/WHEEL
claspin-0.0.1.dist-info/entry_points.txt
claspin-0.0.1.dist-info/licenses/LICENSE
claspin/__init__.py
claspin/cli/__init__.py
claspin/cli/main.py
claspin/model/__init__.py
claspin/model/common.py
claspin/model/metric.py
claspin/py.typed
claspin-0.0.1.dist-info/RECORD
